wamp3py/__init__.py
wamp3py/domain.py
wamp3py/endpoints.py
wamp3py/entrypoints.py
wamp3py/logger.py
wamp3py/peer.py
wamp3py/serializers/__init__.py
wamp3py/serializers/json.py
wamp3py/session.py
wamp3py/shared/__init__.py
wamp3py/shared/new_id.py
wamp3py/shared/observable.py
wamp3py/shared/pending_map.py
wamp3py/shared/retry_strategy.py
wamp3py/transports/__init__.py
wamp3py/transports/interview/__init__.py
wamp3py/transports/interview/http2.py
wamp3py/transports/reconnectable.py
wamp3py/transports/websocket.py
wamp3py-0.5.0.dist-info/LICENSE
wamp3py-0.5.0.dist-info/METADATA
wamp3py-0.5.0.dist-info/WHEEL
wamp3py-0.5.0.dist-info/RECORD
