Metadata-Version: 2.1
Name: wamp3py
Version: 0.5.0
Summary: 
Author: Aidar Turkenov
Author-email: a.k.turken0v@gmail.com
Requires-Python: >=3.12,<4.0
Classifier: Programming Language :: Python :: 3
Classifier: Programming Language :: Python :: 3.12
Requires-Dist: httpx (>=0.26.0,<0.27.0)
Requires-Dist: websockets (>=12.0,<13.0)
